{
	"configurations" : 
	[
		{
			"directories" : 
			[
				{
					"build" : ".",
					"jsonFile" : "directory-.-Debug-f5ebdc15457944623624.json",
					"minimumCMakeVersion" : 
					{
						"string" : "3.30"
					},
					"projectIndex" : 0,
					"source" : ".",
					"targetIndexes" : 
					[
						0
					]
				}
			],
			"name" : "Debug",
			"projects" : 
			[
				{
					"directoryIndexes" : 
					[
						0
					],
					"name" : "MacroPlusPlus",
					"targetIndexes" : 
					[
						0
					]
				}
			],
			"targets" : 
			[
				{
					"directoryIndex" : 0,
					"id" : "MacroPlusPlus::@6890427a1f51a3e7e1df",
					"jsonFile" : "target-MacroPlusPlus-Debug-4ac3d43facbbb18e2e24.json",
					"name" : "MacroPlusPlus",
					"projectIndex" : 0
				}
			]
		}
	],
	"kind" : "codemodel",
	"paths" : 
	{
		"build" : "/home/cj_link/Programming/MacroPlusPlus/cmake-build-debug",
		"source" : "/home/cj_link/Programming/MacroPlusPlus"
	},
	"version" : 
	{
		"major" : 2,
		"minor" : 7
	}
}
